Metadata-Version: 2.1
Name: codeforces
Version: 0.1.1
Summary: A simple command line tool to move your competitive programming workflow to your terminal.
Home-page: https://github.com/Nirlep5252/codeforces-cli
Author: Nirlep5252
License: MIT
Platform: UNKNOWN
Classifier: Programming Language :: Python :: 3
Requires-Python: >=3.7
